{
  "name": "toak0o-up1b8e5",
  "arn": "arn:aws:iam::164357104722:role/toak0o-up1b8e5",
  "service": [
    "edgelambda.amazonaws.com",
    "lambda.amazonaws.com"
  ],
  "policy": {
    "Version": "2012-10-17",
    "Statement": [
      {
        "Effect": "Allow",
        "Resource": "*",
        "Action": [
          "logs:CreateLogGroup",
          "logs:CreateLogStream",
          "logs:PutLogEvents"
        ]
      },
      {
        "Effect": "Allow",
        "Resource": "arn:aws:s3:::toak0o-j1ktfhw/*",
        "Action": [
          "s3:GetObject",
          "s3:PutObject"
        ]
      }
    ]
  },
  "region": "us-east-1"
}